fastapi_views/__init__.py
fastapi_views/settings.py
fastapi_views/types.py
fastapi_views/utils.py
fastapi_views/__pycache__/__init__.cpython-39.pyc
fastapi_views/__pycache__/settings.cpython-39.pyc
fastapi_views/__pycache__/utils.cpython-39.pyc
fastapi_views/ext/__init__.py
fastapi_views/ext/motor/__init__.py
fastapi_views/ext/motor/async_api.py
fastapi_views/ext/motor/core.py
fastapi_views/ext/motor/mixins.py
fastapi_views/ext/motor/pagination/__init__.py
fastapi_views/ext/motor/pagination/core.py
fastapi_views/ext/pymongo/__init__.py
fastapi_views/ext/pymongo/core.py
fastapi_views/ext/pymongo/mixins.py
fastapi_views/ext/pymongo/sync_api.py
fastapi_views/ext/pymongo/pagination/__init__.py
fastapi_views/ext/pymongo/pagination/core.py
fastapi_views/ext/sql_alchemy/__init__.py
fastapi_views/ext/sql_alchemy/async_api.py
fastapi_views/ext/sql_alchemy/core.py
fastapi_views/ext/sql_alchemy/mixins.py
fastapi_views/ext/sql_alchemy/sync_api.py
fastapi_views/ext/sql_alchemy/pagination/__init__.py
fastapi_views/ext/sql_alchemy/pagination/core.py
fastapi_views/pagination/__init__.py
fastapi_views/pagination/annotations.py
fastapi_views/pagination/core.py
fastapi_views/pagination/schema.py
fastapi_views/tests/__init__.py
fastapi_views/tests/_db_sessions.py
fastapi_views/tests/_tmp_db.py
fastapi_views/tests/conftest.py
fastapi_views/tests/test_api.py
fastapi_views/tests/test_async_api.py
fastapi_views/tests/test_motor_api.py
fastapi_views/tests/test_motor_pagination.py
fastapi_views/tests/test_pagination.py
fastapi_views/tests/test_pymongo_api.py
fastapi_views/tests/test_pymongo_pagination.py
fastapi_views/tests/test_utils.py
fastapi_views/tests/__pycache__/__init__.cpython-39.pyc
fastapi_views/tests/__pycache__/_db_sessions.cpython-39.pyc
fastapi_views/tests/__pycache__/_tmp_db.cpython-39.pyc
fastapi_views/tests/__pycache__/test_api.cpython-39-pytest-7.1.2.pyc
fastapi_views/tests/__pycache__/test_async_api.cpython-39-pytest-7.1.2.pyc
fastapi_view_mixins-0.1.1.dist-info/METADATA
fastapi_view_mixins-0.1.1.dist-info/WHEEL
fastapi_view_mixins-0.1.1.dist-info/top_level.txt
fastapi_view_mixins-0.1.1.dist-info/RECORD
