Metadata-Version: 2.1
Name: fastapi-view-mixins
Version: 0.1.1
Summary: Fastapi view mixins
Home-page: UNKNOWN
Author: Patryk Dąbrowski
Author-email: tibiasportex@gmail.com
License: UNKNOWN
Keywords: python,paginator,pagination,views
Platform: UNKNOWN
Classifier: Development Status :: 3 - Alpha
Classifier: Intended Audience :: Education
Classifier: Programming Language :: Python :: 3
Classifier: License :: OSI Approved :: MIT License
Classifier: Operating System :: OS Independent
Requires-Dist: fastapi
Requires-Dist: sqlalchemy
Requires-Dist: pymongo
Requires-Dist: motor
